README.md
setup.cfg
setup.py
fastwire/__init__.py
fastwire/box.py
fastwire/condition.py
fastwire/container.py
fastwire/decorate.py
fastwire/settings.py
fastwire/signal.py
fastwire/wire.py
fastwire/wired.py
fastwire.egg-info/PKG-INFO
fastwire.egg-info/SOURCES.txt
fastwire.egg-info/dependency_links.txt
fastwire.egg-info/top_level.txt
test/test_condition.py
test/test_decorators.py
test/test_performance.py
test/test_signal.py
test/test_signalbox.py
test/test_signalcontainer.py
test/test_wire.py
test/test_wirebox.py
test/test_wirecontainer.py