Metadata-Version: 2.1
Name: fastwire
Version: 0.1.4
Summary: Easy data transfer between classes.
Home-page: https://github.com/pythoro/fastwire.git
Author: Reuben Rusk
Author-email: pythoro@mindquip.com
License: UNKNOWN
Download-URL: https://github.com/pythoro/fastwire/archive/v0.1.4.zip
Keywords: WIRE,CONNECTION,UTILITY
Platform: UNKNOWN
Classifier: Programming Language :: Python :: 3.6
Classifier: Programming Language :: Python :: 3.7
Classifier: Development Status :: 3 - Alpha
Classifier: License :: OSI Approved :: MIT License
Classifier: Operating System :: OS Independent
Classifier: Natural Language :: English
Classifier: Topic :: Software Development :: Libraries :: Python Modules
